requirements.txt
requirements_for_packaging.txt
nipcbatt/__init__.py
nipcbatt/docs/images/Hardware Configuration Utility.png
nipcbatt/docs/images/NI-MAX.png
nipcbatt/docs/images/SVG_to_FDVM_Results.png
nipcbatt/docs/Python PCB Assembly Test Toolkit - Getting Started.pdf
nipcbatt/docs/Python PCB Assembly Test Toolkit - User Manual.pdf
nipcbatt/pcbatt_analysis/__init__.py
nipcbatt/pcbatt_analysis/_pcbatt_analysis_internal/__init__.py
nipcbatt/pcbatt_analysis/_pcbatt_analysis_internal/_analysis_library_info.py
nipcbatt/pcbatt_analysis/_pcbatt_analysis_internal/_analysis_library_interop.py
nipcbatt/pcbatt_analysis/analysis_library_exceptions.py
nipcbatt/pcbatt_analysis/analysis_library_info.py
nipcbatt/pcbatt_analysis/analysis_library_interop.py
nipcbatt/pcbatt_analysis/analysis_library_messages.py
nipcbatt/pcbatt_analysis/common/base_types.py
nipcbatt/pcbatt_analysis/common/common_types.py
nipcbatt/pcbatt_analysis/waveform_analysis/__init__.py
nipcbatt/pcbatt_analysis/waveform_analysis/_waveform_analysis_internal/__init__.py
nipcbatt/pcbatt_analysis/waveform_analysis/_waveform_analysis_internal/_amplitude_and_levels_analysis.py
nipcbatt/pcbatt_analysis/waveform_analysis/_waveform_analysis_internal/_dc_rms_analysis.py
nipcbatt/pcbatt_analysis/waveform_analysis/_waveform_analysis_internal/_frequency_domain_analysis.py
nipcbatt/pcbatt_analysis/waveform_analysis/_waveform_analysis_internal/_pulse_analog_analysis.py
nipcbatt/pcbatt_analysis/waveform_analysis/amplitude_and_levels_analysis.py
nipcbatt/pcbatt_analysis/waveform_analysis/dc_rms_analysis.py
nipcbatt/pcbatt_analysis/waveform_analysis/frequency_domain_analysis.py
nipcbatt/pcbatt_analysis/waveform_analysis/pulse_analog_analysis.py
nipcbatt/pcbatt_analysis/waveform_creation/__init__.py
nipcbatt/pcbatt_analysis/waveform_creation/_waveform_creation_internal/__init__.py
nipcbatt/pcbatt_analysis/waveform_creation/_waveform_creation_internal/_multitones_waveform.py
nipcbatt-1.0.60.dist-info/LICENSE
nipcbatt-1.0.60.dist-info/METADATA
nipcbatt-1.0.60.dist-info/WHEEL
nipcbatt-1.0.60.dist-info/RECORD
