Metadata-Version: 2.1
Name: nipcbatt
Version: 1.0.60
Summary: Python PCB Assembly Test Toolkit
Home-page: https://github.com/ni/nipcbatt
License: MIT
Keywords: nipcbatt,pcbatt,pcba,pcb
Author: NI
Author-email: opensource@ni.com
Maintainer: John Meeker
Maintainer-email: john.meeker@emerson.com
Requires-Python: >=3.9,<4.0
Classifier: Development Status :: 5 - Production/Stable
Classifier: Intended Audience :: Developers
Classifier: Intended Audience :: Manufacturing
Classifier: Intended Audience :: Science/Research
Classifier: License :: OSI Approved :: MIT License
Classifier: Operating System :: Microsoft :: Windows
Classifier: Programming Language :: Python :: 3
Classifier: Programming Language :: Python :: 3.9
Classifier: Programming Language :: Python :: 3.10
Classifier: Programming Language :: Python :: 3.11
Classifier: Programming Language :: Python :: 3.12
Classifier: Programming Language :: Python :: 3.13
Requires-Dist: colorama (==0.4.6)
Requires-Dist: executing (==2.0.1)
Requires-Dist: matplotlib (==3.9.2)
Requires-Dist: nidaqmx (==0.9.0)
Requires-Dist: numpy (==1.26.4)
Requires-Dist: pandas (==2.2.2)
Requires-Dist: pyvisa (==1.14.1)
Requires-Dist: scipy (==1.13.0)
Requires-Dist: varname (==0.12.0)
Project-URL: Repository, https://github.com/ni/nipcbatt
